pmd/__init__.py
pmd/__pycache__/__init__.cpython-39.pyc
pmd/core/Builder.py
pmd/core/Job.py
pmd/core/Lammps.py
pmd/core/Pmd.py
pmd/core/Procedure.py
pmd/core/System.py
pmd/core/__init__.py
pmd/core/__pycache__/Builder.cpython-39.pyc
pmd/core/__pycache__/Job.cpython-39.pyc
pmd/core/__pycache__/Lammps.cpython-39.pyc
pmd/core/__pycache__/Pmd.cpython-39.pyc
pmd/core/__pycache__/Procedure.cpython-39.pyc
pmd/core/__pycache__/System.cpython-39.pyc
pmd/core/__pycache__/__init__.cpython-39.pyc
pmd/entry/__init__.py
pmd/entry/analyze.py
pmd/entry/load.py
pmd/entry/template.py
pmd/entry/__pycache__/__init__.cpython-39.pyc
pmd/entry/__pycache__/analyze.cpython-39.pyc
pmd/entry/__pycache__/load.cpython-39.pyc
pmd/entry/__pycache__/template.cpython-39.pyc
pmd/postprocessing/Analysis.py
pmd/postprocessing/TrajectoryReader.py
pmd/postprocessing/__init__.py
pmd/postprocessing/__pycache__/Analysis.cpython-39.pyc
pmd/postprocessing/__pycache__/TrajectoryReader.cpython-39.pyc
pmd/postprocessing/__pycache__/__init__.cpython-39.pyc
pmd/util/Log.py
pmd/util/Util.py
pmd/util/__init__.py
pmd/util/__pycache__/Log.cpython-39.pyc
pmd/util/__pycache__/Util.cpython-39.pyc
pmd/util/__pycache__/__init__.cpython-39.pyc
pmd-1.5.2.dist-info/LICENSE
pmd-1.5.2.dist-info/METADATA
pmd-1.5.2.dist-info/WHEEL
pmd-1.5.2.dist-info/entry_points.txt
pmd-1.5.2.dist-info/top_level.txt
pmd-1.5.2.dist-info/zip-safe
pmd-1.5.2.dist-info/RECORD
