Metadata-Version: 2.1
Name: pmd
Version: 1.5.2
Summary: Automated generation of LAMMPS data and input files for polymer molecular dynamics simulations
Home-page: https://github.com/kevinshen56714/Polymer-Molecular-Dynamics
Author: Kuan-Hsuan (Kevin) Shen
Author-email: kevinshen56714@gmail.com
License: MIT
Project-URL: Documentation, https://polymer-molecular-dynamics.netlify.app/
Project-URL: Source, https://github.com/kevinshen56714/Polymer-Molecular-Dynamics
Keywords: LAMMPS,Polymer,SMILES,Molecular Dynamics,Simulations
Platform: any
Classifier: Development Status :: 4 - Beta
Classifier: Programming Language :: Python :: 3
Classifier: Programming Language :: Python :: 3.7
Classifier: Programming Language :: Python :: 3.8
Classifier: Programming Language :: Python :: 3.9
Classifier: Programming Language :: Python :: 3.10
Classifier: Topic :: Software Development
Classifier: Topic :: Utilities
Requires-Python: >=3.7
License-File: LICENSE
Requires-Dist: importlib-metadata
Requires-Dist: pyyaml >=5.0
Requires-Dist: numpy >=1.0
Requires-Dist: pandas >=1.0
Requires-Dist: matplotlib >=3.0
Requires-Dist: scipy >=1.0
Requires-Dist: scikit-learn >=1.0
Requires-Dist: rdkit >=2022.3.3
Requires-Dist: emc-pypi >=2023.8.2
Requires-Dist: inquirer >=2.9.2
Provides-Extra: testing
Requires-Dist: setuptools ; extra == 'testing'
Requires-Dist: pytest ; extra == 'testing'
Requires-Dist: pytest-cov ; extra == 'testing'
